stt/__init__.py
nick_stt-0.1.dist-info/METADATA
nick_stt-0.1.dist-info/WHEEL
nick_stt-0.1.dist-info/top_level.txt
nick_stt-0.1.dist-info/RECORD
