Metadata-Version: 2.1
Name: nick-stt
Version: 0.1
Summary: this is speech to text package created by Nikhil Patidar
Author: Nikhil Patidar 
Author-email: nikhilpatidar004@gmail.com
